<?xml version="1.0" encoding="utf-8"?>
<!DOCTYPE hibernate-mapping PUBLIC "-//Hibernate/Hibernate Mapping DTD 3.0//EN"
"http://hibernate.sourceforge.net/hibernate-mapping-3.0.dtd">
<!-- 
    Mapping file autogenerated by MyEclipse Persistence Tools
-->
<hibernate-mapping>
    <class name="www.quality.model.TblTsrysj" table="TBLTSRYSJ">
        <id name="id" type="java.lang.Integer">
            <column name="ID" precision="9" scale="0" />
            <generator class="sequence">
            	<param name="sequence">SEQ_TBLTSRYSJ</param>
            </generator>
        </id>
        <property name="flid" type="java.lang.Integer">
            <column name="FLID" precision="9" scale="0" />
        </property>
        <property name="sfz" type="java.lang.String">
            <column name="SFZ" />
        </property>
        <property name="s1" type="java.lang.String">
            <column name="S1" />
        </property>
        <property name="s2" type="java.lang.String">
            <column name="S2" />
        </property>
        <property name="s3" type="java.lang.String">
            <column name="S3" />
        </property>
        <property name="s4" type="java.lang.String">
            <column name="S4" />
        </property>
        <property name="s5" type="java.lang.String">
            <column name="S5" />
        </property>
        <property name="s6" type="java.lang.String">
            <column name="S6" />
        </property>
        <property name="s7" type="java.lang.String">
            <column name="S7" />
        </property>
        <property name="s8" type="java.lang.String">
            <column name="S8" />
        </property>
        <property name="s9" type="java.lang.String">
            <column name="S9" />
        </property>
        <property name="s10" type="java.lang.String">
            <column name="S10" />
        </property>
        <property name="s11" type="java.lang.String">
            <column name="S11" />
        </property>
        <property name="s12" type="java.lang.String">
            <column name="S12" />
        </property>
        <property name="s13" type="java.lang.String">
            <column name="S13" />
        </property>
        <property name="s14" type="java.lang.String">
            <column name="S14" />
        </property>
        <property name="s15" type="java.lang.String">
            <column name="S15" />
        </property>
        <property name="s16" type="java.lang.String">
            <column name="S16" />
        </property>
        <property name="s17" type="java.lang.String">
            <column name="S17" />
        </property>
        <property name="s18" type="java.lang.String">
            <column name="S18" />
        </property>
        <property name="s19" type="java.lang.String">
            <column name="S19" />
        </property>
        <property name="s20" type="java.lang.String">
            <column name="S20" />
        </property>
        <property name="s21" type="java.lang.String">
            <column name="S21" />
        </property>
        <property name="s22" type="java.lang.String">
            <column name="S22" />
        </property>
        <property name="s23" type="java.lang.String">
            <column name="S23" />
        </property>
        <property name="s24" type="java.lang.String">
            <column name="S24" />
        </property>
        <property name="s25" type="java.lang.String">
            <column name="S25" />
        </property>
        <property name="s26" type="java.lang.String">
            <column name="S26" />
        </property>
        <property name="s27" type="java.lang.String">
            <column name="S27" />
        </property>
        <property name="s28" type="java.lang.String">
            <column name="S28" />
        </property>
        <property name="s29" type="java.lang.String">
            <column name="S29" />
        </property>
        <property name="s30" type="java.lang.String">
            <column name="S30" />
        </property>
        <property name="s31" type="java.lang.String">
            <column name="S31" />
        </property>
        <property name="s32" type="java.lang.String">
            <column name="S32" />
        </property>
        <property name="s33" type="java.lang.String">
            <column name="S33" />
        </property>
        <property name="s34" type="java.lang.String">
            <column name="S34" />
        </property>
        <property name="s35" type="java.lang.String">
            <column name="S35" />
        </property>
        <property name="s36" type="java.lang.String">
            <column name="S36" />
        </property>
        <property name="s37" type="java.lang.String">
            <column name="S37" />
        </property>
        <property name="s38" type="java.lang.String">
            <column name="S38" />
        </property>
        <property name="s39" type="java.lang.String">
            <column name="S39" />
        </property>
        <property name="s40" type="java.lang.String">
            <column name="S40" />
        </property>
        <property name="s41" type="java.lang.String">
            <column name="S41" />
        </property>
        <property name="s42" type="java.lang.String">
            <column name="S42" />
        </property>
        <property name="s43" type="java.lang.String">
            <column name="S43" />
        </property>
        <property name="s44" type="java.lang.String">
            <column name="S44" />
        </property>
        <property name="s45" type="java.lang.String">
            <column name="S45" />
        </property>
        <property name="s46" type="java.lang.String">
            <column name="S46" />
        </property>
        <property name="s47" type="java.lang.String">
            <column name="S47" />
        </property>
        <property name="s48" type="java.lang.String">
            <column name="S48" />
        </property>
        <property name="s49" type="java.lang.String">
            <column name="S49" />
        </property>
        <property name="s50" type="java.lang.String">
            <column name="S50" />
        </property>
        <property name="s51" type="java.lang.String">
            <column name="S51" />
        </property>
        <property name="s52" type="java.lang.String">
            <column name="S52" />
        </property>
        <property name="s53" type="java.lang.String">
            <column name="S53" />
        </property>
        <property name="s54" type="java.lang.String">
            <column name="S54" />
        </property>
        <property name="s55" type="java.lang.String">
            <column name="S55" />
        </property>
        <property name="s56" type="java.lang.String">
            <column name="S56" />
        </property>
        <property name="s57" type="java.lang.String">
            <column name="S57" />
        </property>
        <property name="s58" type="java.lang.String">
            <column name="S58" />
        </property>
        <property name="s59" type="java.lang.String">
            <column name="S59" />
        </property>
        <property name="s60" type="java.lang.String">
            <column name="S60" />
        </property>
        <property name="s61" type="java.lang.String">
            <column name="S61" />
        </property>
        <property name="s62" type="java.lang.String">
            <column name="S62" />
        </property>
        <property name="s63" type="java.lang.String">
            <column name="S63" />
        </property>
        <property name="s64" type="java.lang.String">
            <column name="S64" />
        </property>
        <property name="s65" type="java.lang.String">
            <column name="S65" />
        </property>
        <property name="s66" type="java.lang.String">
            <column name="S66" />
        </property>
        <property name="s67" type="java.lang.String">
            <column name="S67" />
        </property>
        <property name="s68" type="java.lang.String">
            <column name="S68" />
        </property>
        <property name="s69" type="java.lang.String">
            <column name="S69" />
        </property>
        <property name="s70" type="java.lang.String">
            <column name="S70" />
        </property>
        <property name="s71" type="java.lang.String">
            <column name="S71" />
        </property>
        <property name="s72" type="java.lang.String">
            <column name="S72" />
        </property>
        <property name="s73" type="java.lang.String">
            <column name="S73" />
        </property>
        <property name="s74" type="java.lang.String">
            <column name="S74" />
        </property>
        <property name="s75" type="java.lang.String">
            <column name="S75" />
        </property>
        <property name="s76" type="java.lang.String">
            <column name="S76" />
        </property>
        <property name="s77" type="java.lang.String">
            <column name="S77" />
        </property>
        <property name="s78" type="java.lang.String">
            <column name="S78" />
        </property>
        <property name="s79" type="java.lang.String">
            <column name="S79" />
        </property>
        <property name="s80" type="java.lang.String">
            <column name="S80" />
        </property>
        <property name="s81" type="java.lang.String">
            <column name="S81" />
        </property>
        <property name="s82" type="java.lang.String">
            <column name="S82" />
        </property>
        <property name="s83" type="java.lang.String">
            <column name="S83" />
        </property>
        <property name="s84" type="java.lang.String">
            <column name="S84" />
        </property>
        <property name="s85" type="java.lang.String">
            <column name="S85" />
        </property>
        <property name="s86" type="java.lang.String">
            <column name="S86" />
        </property>
        <property name="s87" type="java.lang.String">
            <column name="S87" />
        </property>
        <property name="s88" type="java.lang.String">
            <column name="S88" />
        </property>
        <property name="s89" type="java.lang.String">
            <column name="S89" />
        </property>
        <property name="s90" type="java.lang.String">
            <column name="S90" />
        </property>
        <property name="s91" type="java.lang.String">
            <column name="S91" />
        </property>
        <property name="s92" type="java.lang.String">
            <column name="S92" />
        </property>
        <property name="s93" type="java.lang.String">
            <column name="S93" />
        </property>
        <property name="s94" type="java.lang.String">
            <column name="S94" />
        </property>
        <property name="s95" type="java.lang.String">
            <column name="S95" />
        </property>
        <property name="s96" type="java.lang.String">
            <column name="S96" />
        </property>
        <property name="s97" type="java.lang.String">
            <column name="S97" />
        </property>
        <property name="s98" type="java.lang.String">
            <column name="S98" />
        </property>
        <property name="s99" type="java.lang.String">
            <column name="S99" />
        </property>
        <property name="s100" type="java.lang.String">
            <column name="S100" />
        </property>
        <!-- <property name="ryname" type="java.lang.String">
            <column name="RYNAME" />
        </property> -->
        <property name="ryname" type="java.lang.String" formula="(select max(jm.name) from SYSDIC_JUMINXINXI jm where jm.ID_NUMBER=sfz)">
        </property>
        <property name="flname" type="java.lang.String" formula="(select max(fl.name) from TblTsryfl fl where fl.id=flid)">
        </property>
    </class>
</hibernate-mapping>
